README.rst
setup.cfg
setup.py
WHIPS3.egg-info/PKG-INFO
WHIPS3.egg-info/SOURCES.txt
WHIPS3.egg-info/dependency_links.txt
WHIPS3.egg-info/requires.txt
WHIPS3.egg-info/top_level.txt
process_sat/__init__.py
process_sat/filetypes.py
process_sat/function_unittests.py
process_sat/grid_geo.py
process_sat/map_geo.py
process_sat/map_helpers.py
process_sat/out_geo.py
process_sat/parse_geo.py
process_sat/utils.py
process_sat/whips.py