Metadata-Version: 1.1
Name: WHIPS3
Version: 3.1.1
Summary: Scripts for customized regridding of Level-2 data to Level-3 data
Home-page: https://nelson.wisc.edu/sage/data-and-models/software.php
Author: Tracey Holloway, Jacob Oberman, Peidong Wang
Author-email: taholloway@wisc.edu
License: MIT License
Download-URL: https://github.com/WHIPS-team/WHIPS3/archive/3.1.1.tar.gz
Platform: UNKNOWN
Classifier: Development Status :: 4 - Beta
Classifier: Intended Audience :: Science/Research
Classifier: Natural Language :: English
Classifier: Programming Language :: Python
